cryptoengine-1.0.3.dist-info/licenses/LICENSE
ssh_encryptor/app.py
ssh_encryptor/assets/icon-128.ico
ssh_encryptor/assets/icon-16.ico
ssh_encryptor/assets/icon-256.ico
ssh_encryptor/assets/icon-32.ico
ssh_encryptor/assets/icon-48.ico
ssh_encryptor/assets/icon-64.ico
ssh_encryptor/assets/icon.icns
ssh_encryptor/assets/icon.ico
ssh_encryptor/assets/icon.png
ssh_encryptor/assets/me.jpeg
ssh_encryptor/crypto/hash_utils.py
ssh_encryptor/crypto/rsa_hybrid.py
ssh_encryptor/crypto/sign_utils.py
ssh_encryptor/keys/storage.py
ssh_encryptor/ui/dialogs.py
ssh_encryptor/ui/main_window.py
ssh_encryptor/ui/toast.py
ssh_encryptor/ui/tabs/about_tab.py
ssh_encryptor/ui/tabs/decrypt_tab.py
ssh_encryptor/ui/tabs/encrypt_tab.py
ssh_encryptor/ui/tabs/hashing_tab.py
ssh_encryptor/ui/tabs/keys_tab.py
ssh_encryptor/ui/tabs/metadata_tab.py
ssh_encryptor/ui/tabs/sign_tab.py
cryptoengine-1.0.3.dist-info/METADATA
cryptoengine-1.0.3.dist-info/WHEEL
cryptoengine-1.0.3.dist-info/entry_points.txt
cryptoengine-1.0.3.dist-info/top_level.txt
cryptoengine-1.0.3.dist-info/RECORD
