Metadata-Version: 2.4
Name: cryptoengine
Version: 1.0.3
Summary: CryptoEngine — Secure Encryption & Signing Toolkit
Author-email: Harshana Chathuranga <wmhchathuranga@bitrate.lk>
License: MIT
Project-URL: Homepage, https://github.com/wmhchathuranga/crypto_engine
Keywords: cryptography,ssh,rsa,aes,signing,security
Classifier: Programming Language :: Python :: 3
Classifier: License :: OSI Approved :: MIT License
Classifier: Operating System :: OS Independent
Requires-Python: >=3.10
License-File: LICENSE
Requires-Dist: pyqt6
Requires-Dist: cryptography
Requires-Dist: pillow>=10.0.0
Dynamic: license-file
